{"cameraMode":{"drawMode":0,"name":"Shaded","section":"Shading Mode"},"sceneLighting":false,"audioPlay":false,"sceneViewState":{"showFog":true,"showMaterialUpdate":false,"showSkybox":false,"showFlares":true,"showImageEffects":true,"showParticleSystems":true},"in2DMode":false,"pivot":{"x":4.832979679107666,"y":-0.1262320727109909,"z":-0.33583641052246096},"rotation":{"x":-0.004623548127710819,"y":-0.9419363141059876,"z":0.33564943075180056,"w":-0.013334600254893303},"size":2.991931438446045,"orthographic":false}